README.md
setup.cfg
setup.py
po_distributions/Binomialdistribution.py
po_distributions/Gaussiandistribution.py
po_distributions/Generaldistribution.py
po_distributions/__init__.py
po_distributions.egg-info/PKG-INFO
po_distributions.egg-info/SOURCES.txt
po_distributions.egg-info/dependency_links.txt
po_distributions.egg-info/not-zip-safe
po_distributions.egg-info/top_level.txt